fastapi_login/__init__.py
fastapi_login/exceptions.py
fastapi_login/fastapi_login.py
fastapi_login/py.typed
fastapi_login/secrets.py
fastapi_login/utils.py
tests/__init__.py
tests/conftest.py
tests/test_basic_functionality.py
tests/test_dependency.py
tests/test_secret.py
tests/test_advanced/__init__.py
tests/test_advanced/test_exception_handling.py
tests/test_advanced/test_middleware.py
fastapi_login-1.8.2.dist-info/LICENSE
fastapi_login-1.8.2.dist-info/METADATA
fastapi_login-1.8.2.dist-info/WHEEL
fastapi_login-1.8.2.dist-info/top_level.txt
fastapi_login-1.8.2.dist-info/RECORD
