Metadata-Version: 2.1
Name: fastapi-login
Version: 1.8.2
Summary: UNKNOWN
Home-page: https://github.com/MushroomMaula/fastapi_login
Author: Max Rausch-Dupont
Author-email: maxrd79@gmail.com
License: UNKNOWN
Platform: UNKNOWN
Classifier: Programming Language :: Python :: 3
Classifier: License :: OSI Approved :: MIT License
Classifier: Operating System :: OS Independent
License-File: LICENSE
